opentf/commons/__init__.py
opentf/commons/auth.py
opentf/commons/config.py
opentf/commons/exceptions.py
opentf/commons/expressions.py
opentf/commons/meta.py
opentf/commons/pubsub.py
opentf/commons/schemas.py
opentf/commons/selectors.py
opentf/schemas/__init__.py
opentf/schemas/abac.opentestfactory.org/v1alpha1/Policy.json
opentf/schemas/config.opentestfactory.org/v1/Descriptor.json
opentf/schemas/opentestfactory.org/v1/ExecutionCommand.json
opentf/schemas/opentestfactory.org/v1/ExecutionResult.json
opentf/schemas/opentestfactory.org/v1/GeneratorResult.json
opentf/schemas/opentestfactory.org/v1/ProviderCommand.json
opentf/schemas/opentestfactory.org/v1/ProviderResult.json
opentf/schemas/opentestfactory.org/v1/Subscription.json
opentf/schemas/opentestfactory.org/v1/Workflow.json
opentf/schemas/opentestfactory.org/v1/WorkflowCanceled.json
opentf/schemas/opentestfactory.org/v1/WorkflowCancellation.json
opentf/schemas/opentestfactory.org/v1/WorkflowCompleted.json
opentf/schemas/opentestfactory.org/v1alpha1/AgentRegistration.json
opentf/schemas/opentestfactory.org/v1alpha1/AllureCollectorOutput.json
opentf/schemas/opentestfactory.org/v1alpha1/ChannelHandlerHooks.json
opentf/schemas/opentestfactory.org/v1alpha1/EventBusConfig.json
opentf/schemas/opentestfactory.org/v1alpha1/ExecutionCommand.json
opentf/schemas/opentestfactory.org/v1alpha1/ExecutionError.json
opentf/schemas/opentestfactory.org/v1alpha1/ExecutionResult.json
opentf/schemas/opentestfactory.org/v1alpha1/GeneratorCommand.json
opentf/schemas/opentestfactory.org/v1alpha1/GeneratorResult.json
opentf/schemas/opentestfactory.org/v1alpha1/InsightCollector.json
opentf/schemas/opentestfactory.org/v1alpha1/Notification.json
opentf/schemas/opentestfactory.org/v1alpha1/PluginMetadata.json
opentf/schemas/opentestfactory.org/v1alpha1/ProviderCommand.json
opentf/schemas/opentestfactory.org/v1alpha1/ProviderConfig.json
opentf/schemas/opentestfactory.org/v1alpha1/ProviderResult.json
opentf_toolkit_nightly-0.63.0.dev1431.dist-info/licenses/LICENSE
opentf_toolkit_nightly-0.63.0.dev1431.dist-info/METADATA
opentf_toolkit_nightly-0.63.0.dev1431.dist-info/WHEEL
opentf_toolkit_nightly-0.63.0.dev1431.dist-info/top_level.txt
opentf_toolkit_nightly-0.63.0.dev1431.dist-info/RECORD
