Metadata-Version: 2.4
Name: opentf-toolkit-nightly
Version: 0.63.0.dev1431
Summary: OpenTestFactory Orchestrator Toolkit
Home-page: https://gitlab.com/henixdevelopment/open-source/opentestfactory/python-toolkit
Author: Martin Lafaix
Author-email: mlafaix@henix.com
Maintainer: Henix
Maintainer-email: opentestfactory@henix.com
License: Apache Software License (https://www.apache.org/licenses/LICENSE-2.0)
Classifier: Development Status :: 4 - Beta
Classifier: Programming Language :: Python :: 3
Classifier: Operating System :: OS Independent
Classifier: Topic :: Software Development :: Libraries
Classifier: License :: OSI Approved :: Apache Software License
Requires-Python: >= 3.9.0
License-File: LICENSE
Requires-Dist: requests>=2.32
Requires-Dist: PyJWT[crypto]>=2.9
Requires-Dist: PyYAML>=6
Requires-Dist: Flask<4,>=3
Requires-Dist: jsonschema>=4.23
Requires-Dist: toposort>=1.10
Requires-Dist: waitress>=3
Requires-Dist: paste>=3.10
Dynamic: author
Dynamic: author-email
Dynamic: classifier
Dynamic: description
Dynamic: description-content-type
Dynamic: home-page
Dynamic: license
Dynamic: license-file
Dynamic: maintainer
Dynamic: maintainer-email
Dynamic: requires-dist
Dynamic: requires-python
Dynamic: summary
